ssl_smtp_handler/__init__.py
ssl_smtp_handler-1.0.4.dist-info/LICENSE
ssl_smtp_handler-1.0.4.dist-info/WHEEL
ssl_smtp_handler-1.0.4.dist-info/METADATA
ssl_smtp_handler-1.0.4.dist-info/RECORD
