Metadata-Version: 2.1
Name: ssl-smtp-handler
Version: 1.0.4
Summary: A standard library compatible logging handler which sends mail via SMTP_SSL
Home-page: https://github.com/dycw/ssl-smtp-handler
License: MIT
Author: Derek Wan
Author-email: d.wan@icloud.com
Requires-Python: >=3.6.1,<4.0.0
Classifier: License :: OSI Approved :: MIT License
Classifier: Programming Language :: Python :: 3
Classifier: Programming Language :: Python :: 3.7
Classifier: Programming Language :: Python :: 3.8
Classifier: Programming Language :: Python :: 3.9
